AUTHORS
LICENSE
MANIFEST.in
README.rst
setup.py
django_cms_storelocator.egg-info/PKG-INFO
django_cms_storelocator.egg-info/SOURCES.txt
django_cms_storelocator.egg-info/dependency_links.txt
django_cms_storelocator.egg-info/not-zip-safe
django_cms_storelocator.egg-info/requires.txt
django_cms_storelocator.egg-info/top_level.txt
store_locator/__init__.py
store_locator/admin.py
store_locator/cms_app.py
store_locator/cms_plugins.py
store_locator/models.py
store_locator/urls.py
store_locator/views.py
store_locator/migrations/0001_initial.py
store_locator/migrations/0002_auto__chg_field_location_phone__chg_field_location_address.py
store_locator/migrations/0003_auto__add_storelocator.py
store_locator/migrations/0004_auto__del_field_storelocator_distance__add_field_storelocator_default_.py
store_locator/migrations/0005_auto__del_field_storelocator_start_location__add_field_storelocator_ad.py
store_locator/migrations/0006_auto__del_field_storelocator_longitude__del_field_storelocator_address.py
store_locator/migrations/0007_auto__add_locationtype__add_field_location_location_type.py
store_locator/migrations/0008_auto__del_field_location_location_type.py
store_locator/migrations/0009_auto__add_field_storelocator_show_distance.py
store_locator/migrations/0010_auto.py
store_locator/migrations/__init__.py
store_locator/static/store_locator/js/store_locator_admin.js
store_locator/static/store_locator/js/store_locator_map.js
store_locator/templates/store_locator/store_locator_map.html
store_locator/templates/store_locator/store_locator_map_view.html