Metadata-Version: 1.1
Name: django-cms-storelocator
Version: 1.10.0
Summary: A store locator extension for Django CMS
Home-page: http://github.com/megamark16/django-cms-storelocator
Author: Mark Ransom
Author-email: megamark16@gmail.com
License: BSD
Platform: OS Independent
Classifier: Development Status :: 4 - Beta
Classifier: Framework :: Django
Classifier: Intended Audience :: Developers
Classifier: License :: OSI Approved :: BSD License
Classifier: Operating System :: OS Independent
Classifier: Programming Language :: Python
Classifier: Topic :: Internet :: WWW/HTTP
Classifier: Topic :: Internet :: WWW/HTTP :: Dynamic Content
